MANIFEST.in
README.rst
setup.py
imageset/__init__.py
imageset/imageset.py
imageset.egg-info/PKG-INFO
imageset.egg-info/SOURCES.txt
imageset.egg-info/dependency_links.txt
imageset.egg-info/entry_points.txt
imageset.egg-info/not-zip-safe
imageset.egg-info/requires.txt
imageset.egg-info/top_level.txt
imageset/templates/ObjCCategory.h.mustache
imageset/templates/ObjCCategory.m.mustache
imageset/templates/ObjCConstants.h.mustache
imageset/templates/ObjCConstants.m.mustache
imageset/templates/ObjCFunctions.h.mustache
imageset/templates/ObjCFunctions.m.mustache
imageset/templates/SwiftConstants.swift.mustache
imageset/templates/SwiftExtension.swift.mustache
imageset/templates/SwiftFunctions.swift.mustache