Metadata-Version: 1.0
Name: imageset
Version: 1.2
Summary: Process Xcode imagesets into compiler-checkable files
Home-page: http://github.com/natestedman/imageset
Author: Nate Stedman
Author-email: nate@natestedman.com
License: ISC
Platform: UNKNOWN
